doc/AUTHORS
doc/ChangeLog_Wapiti
doc/ChangeLog_lswww
doc/FAQ.md
doc/cookie.ico
doc/cookies_and_scripts_auth.md
doc/docker-compose.dummy.yml
doc/endpoints.md
doc/example.txt
doc/integration_system.md
doc/wapiti-getcookie.1
doc/wapiti-getcookie.1.html
doc/wapiti-getcookie.ronn
doc/wapiti.1
doc/wapiti.1.html
doc/wapiti.ico
doc/wapiti.ronn
doc/xxe_module.md
wapiti3-3.2.10.dist-info/licenses/LICENSE
wapitiCore/__init__.py
wapitiCore/moon.py
wapitiCore/attack/__init__.py
wapitiCore/attack/active_scanner.py
wapitiCore/attack/attack.py
wapitiCore/attack/mod_backup.py
wapitiCore/attack/mod_brute_login_form.py
wapitiCore/attack/mod_buster.py
wapitiCore/attack/mod_cms.py
wapitiCore/attack/mod_crlf.py
wapitiCore/attack/mod_csrf.py
wapitiCore/attack/mod_exec.py
wapitiCore/attack/mod_file.py
wapitiCore/attack/mod_htaccess.py
wapitiCore/attack/mod_htp.py
wapitiCore/attack/mod_ldap.py
wapitiCore/attack/mod_log4shell.py
wapitiCore/attack/mod_methods.py
wapitiCore/attack/mod_network_device.py
wapitiCore/attack/mod_nikto.py
wapitiCore/attack/mod_permanentxss.py
wapitiCore/attack/mod_redirect.py
wapitiCore/attack/mod_shellshock.py
wapitiCore/attack/mod_spring4shell.py
wapitiCore/attack/mod_sql.py
wapitiCore/attack/mod_ssl.py
wapitiCore/attack/mod_ssrf.py
wapitiCore/attack/mod_takeover.py
wapitiCore/attack/mod_timesql.py
wapitiCore/attack/mod_upload.py
wapitiCore/attack/mod_wapp.py
wapitiCore/attack/mod_wp_enum.py
wapitiCore/attack/mod_xss.py
wapitiCore/attack/mod_xxe.py
wapitiCore/attack/passive_scanner.py
wapitiCore/attack/cms/cms_common.py
wapitiCore/attack/cms/mod_drupal_enum.py
wapitiCore/attack/cms/mod_joomla_enum.py
wapitiCore/attack/cms/mod_prestashop_enum.py
wapitiCore/attack/cms/mod_spip_enum.py
wapitiCore/attack/cms/mod_wp_enum.py
wapitiCore/attack/cve/checker.py
wapitiCore/attack/modules/__init__.py
wapitiCore/attack/modules/core.py
wapitiCore/attack/modules/passive/__init__.py
wapitiCore/attack/modules/passive/mod_cookie_flags.py
wapitiCore/attack/modules/passive/mod_csp.py
wapiti3-3.2.10.dist-info/METADATA
wapiti3-3.2.10.dist-info/WHEEL
wapiti3-3.2.10.dist-info/entry_points.txt
wapiti3-3.2.10.dist-info/top_level.txt
wapiti3-3.2.10.dist-info/RECORD
